Metadata-Version: 1.0
Name: testupload
Version: 0.0.1
Summary: just a test
Home-page: UNKNOWN
Author: UNKNOWN
Author-email: UNKNOWN
License: UNKNOWN
Platform: UNKNOWN
